qcmd/core.py
qcmd/exceptions.py
qcmd/processors/executor.py
qcmd-0.0.5rc4.dist-info/LICENSE
qcmd-0.0.5rc4.dist-info/METADATA
qcmd-0.0.5rc4.dist-info/WHEEL
qcmd-0.0.5rc4.dist-info/top_level.txt
qcmd-0.0.5rc4.dist-info/RECORD
