Metadata-Version: 2.1
Name: qcmd
Version: 0.0.5rc4
Summary: qcmd from libanvl
Home-page: https://github.com/libanvl/python-qcmd
Maintainer: libanvl
Maintainer-email: hammer@libanvl.dev
License: MIT License
Keywords: libanvl,qcmd,threadpoolexecutor,executor
Platform: UNKNOWN
Classifier: Development Status :: 3 - Alpha
Classifier: License :: OSI Approved :: MIT License
Classifier: Operating System :: POSIX :: Linux
Classifier: Programming Language :: Python :: 3.8
Classifier: Topic :: Software Development :: Libraries
Classifier: Topic :: Utilities
Classifier: Typing :: Typed
